MANIFEST.in
README.md
README.txt
setup.py
django_zurb_foundation.egg-info/PKG-INFO
django_zurb_foundation.egg-info/SOURCES.txt
django_zurb_foundation.egg-info/dependency_links.txt
django_zurb_foundation.egg-info/not-zip-safe
django_zurb_foundation.egg-info/top_level.txt
foundation/__init__.py
foundation/urls.py
foundation/static/foundation/css/foundation-icons.css
foundation/static/foundation/css/foundation-icons.eot
foundation/static/foundation/css/foundation-icons.svg
foundation/static/foundation/css/foundation-icons.ttf
foundation/static/foundation/css/foundation-icons.woff
foundation/static/foundation/css/foundation.css
foundation/static/foundation/css/foundation.min.css
foundation/static/foundation/css/normalize.css
foundation/static/foundation/img/.gitkeep
foundation/static/foundation/js/foundation.min.js
foundation/static/foundation/js/foundation/foundation.abide.js
foundation/static/foundation/js/foundation/foundation.accordion.js
foundation/static/foundation/js/foundation/foundation.alert.js
foundation/static/foundation/js/foundation/foundation.clearing.js
foundation/static/foundation/js/foundation/foundation.dropdown.js
foundation/static/foundation/js/foundation/foundation.equalizer.js
foundation/static/foundation/js/foundation/foundation.interchange.js
foundation/static/foundation/js/foundation/foundation.joyride.js
foundation/static/foundation/js/foundation/foundation.js
foundation/static/foundation/js/foundation/foundation.magellan.js
foundation/static/foundation/js/foundation/foundation.offcanvas.js
foundation/static/foundation/js/foundation/foundation.orbit.js
foundation/static/foundation/js/foundation/foundation.reveal.js
foundation/static/foundation/js/foundation/foundation.slider.js
foundation/static/foundation/js/foundation/foundation.tab.js
foundation/static/foundation/js/foundation/foundation.tooltip.js
foundation/static/foundation/js/foundation/foundation.topbar.js
foundation/static/foundation/js/vendor/fastclick.js
foundation/static/foundation/js/vendor/jquery.cookie.js
foundation/static/foundation/js/vendor/jquery.js
foundation/static/foundation/js/vendor/modernizr.js
foundation/static/foundation/js/vendor/placeholder.js
