Metadata-Version: 1.1
Name: django-zurb-foundation
Version: 5.3.0
Summary: Django Zurb Foundation package.
Home-page: https://github.com/amarsahinovic/django-zurb-foundation
Author: Amar Šahinović
Author-email: amar@sahinovic.com
License: BSD License
Platform: UNKNOWN
Classifier: Environment :: Web Environment
Classifier: Framework :: Django
Classifier: Intended Audience :: Developers
Classifier: License :: OSI Approved :: BSD License
Classifier: Operating System :: OS Independent
Classifier: Programming Language :: Python
Classifier: Topic :: Utilities
